climapan_lab/__init__.py
climapan_lab/base_params.py
climapan_lab/calibrate_model.py
climapan_lab/model.py
climapan_lab/optimized_params.py
climapan_lab/run_sim.py
climapan_lab/validate_sim.py
climapan_lab/analysis/__init__.py
climapan_lab/analysis/inspect_results.py
climapan_lab/analysis/sensitivity_analyzer.py
climapan_lab/analysis/sensitivity_params.py
climapan_lab/analysis/validation_params.py
climapan_lab/data/Germany9122.csv
climapan_lab/data/RCP8-5.csv
climapan_lab/data/germany9120.csv
climapan_lab/data/germany_multi_var.csv
climapan_lab/data/sample_real_data.csv
climapan_lab/docs/__init__.py
climapan_lab/docs/econmodel_uml_diagram_simplified.puml
climapan_lab/docs/uml_diagram.py
climapan_lab/examples/Load_data.py
climapan_lab/examples/__init__.py
climapan_lab/examples/basic_simulation.py
climapan_lab/examples/scenario.py
climapan_lab/examples/simple_example.py
climapan_lab/src/__init__.py
climapan_lab/src/ambr_patch.py
climapan_lab/src/models.py
climapan_lab/src/params.py
climapan_lab/src/utils.py
climapan_lab/src/agents/__init__.py
climapan_lab/src/banks/Bank.py
climapan_lab/src/banks/__init__.py
climapan_lab/src/climate/Climate.py
climapan_lab/src/climate/__init__.py
climapan_lab/src/consumers/Consumer.py
climapan_lab/src/consumers/__init__.py
climapan_lab/src/firms/BrownEnergyFirm.py
climapan_lab/src/firms/CapitalGoodsFirm.py
climapan_lab/src/firms/ConsumerGoodsFirm.py
climapan_lab/src/firms/EnergyFirmBase.py
climapan_lab/src/firms/GoodsFirmBase.py
climapan_lab/src/firms/GreenEnergyFirm.py
climapan_lab/src/firms/__init__.py
climapan_lab/src/governments/Goverment.py
climapan_lab/src/governments/__init__.py
climapan_lab-0.1.0.dist-info/licenses/LICENSE
climapan_lab-0.1.0.dist-info/METADATA
climapan_lab-0.1.0.dist-info/WHEEL
climapan_lab-0.1.0.dist-info/entry_points.txt
climapan_lab-0.1.0.dist-info/top_level.txt
climapan_lab-0.1.0.dist-info/RECORD
