Metadata-Version: 2.4
Name: climapan-lab
Version: 0.1.0
Summary: Climate-Pandemic Economic Modeling Laboratory
Home-page: https://github.com/a11to1n3/climapan-lab
Author: CliMaPan-Lab Team
Author-email: CliMaPan-Lab Team <anh-duy.pham@uni-wuerzburg.de>
License: MIT License
Project-URL: Homepage, https://github.com/a11to1n3/CliMaPan-Lab
Project-URL: Bug Reports, https://github.com/a11to1n3/CliMaPan-Lab/issues
Project-URL: Source, https://github.com/a11to1n3/CliMaPan-Lab
Project-URL: Documentation, https://climapan-lab.readthedocs.io/
Keywords: economics,climate,pandemic,agent-based-modeling,simulation
Classifier: Development Status :: 3 - Alpha
Classifier: Intended Audience :: Science/Research
Classifier: License :: OSI Approved :: MIT License
Classifier: Operating System :: OS Independent
Classifier: Programming Language :: Python :: 3
Classifier: Programming Language :: Python :: 3.8
Classifier: Programming Language :: Python :: 3.9
Classifier: Programming Language :: Python :: 3.10
Classifier: Programming Language :: Python :: 3.11
Classifier: Topic :: Scientific/Engineering :: Artificial Intelligence
Classifier: Topic :: Scientific/Engineering :: Mathematics
Requires-Python: >=3.8
License-File: LICENSE
Requires-Dist: numpy>=1.21.0
Requires-Dist: pandas>=1.3.0
Requires-Dist: matplotlib>=3.5.0
Requires-Dist: ambr>=0.1.5
Requires-Dist: scikit-learn>=1.0.0
Requires-Dist: scipy>=1.7.0
Requires-Dist: joblib>=1.1.0
Requires-Dist: salib>=1.4.0
Requires-Dist: networkx>=2.6.0
Requires-Dist: pathos>=0.2.8
Requires-Dist: dill>=0.3.4
Requires-Dist: h5py>=3.7.0
Requires-Dist: statsmodels>=0.13.0
Requires-Dist: plotly>=5.0
Provides-Extra: dev
Requires-Dist: pytest>=7.0; extra == "dev"
Requires-Dist: pytest-cov>=4.0; extra == "dev"
Requires-Dist: pytest-mock>=3.10; extra == "dev"
Requires-Dist: black>=22.0; extra == "dev"
Requires-Dist: flake8>=5.0; extra == "dev"
Requires-Dist: isort>=5.0; extra == "dev"
Requires-Dist: pre-commit>=2.20; extra == "dev"
Provides-Extra: docs
Requires-Dist: sphinx>=7.0; extra == "docs"
Requires-Dist: sphinx-rtd-theme>=2.0; extra == "docs"
Requires-Dist: myst-parser>=2.0; extra == "docs"
Requires-Dist: sphinx-autodoc-typehints>=1.24; extra == "docs"
Dynamic: author
Dynamic: home-page
Dynamic: license-file
Dynamic: requires-python
